cm_jupyter_widget/__init__.py
cm_jupyter_widget/index.js
cm_jupyter_widget/widget.py
cm_jupyter_widget/.ipynb_checkpoints/widget-checkpoint.py
cm_jupyter_widget-0.3.8.dist-info/WHEEL
cm_jupyter_widget-0.3.8.dist-info/METADATA
cm_jupyter_widget-0.3.8.dist-info/RECORD
