Metadata-Version: 2.4
Name: cm-jupyter-widget
Version: 0.3.8
Summary: CleverMaps Marimo Widget - A widget for embedding CleverMaps visualizations in Marimo notebooks.
Author-email: Karel Psota <karel.psota@clevermaps.io>
Requires-Python: >=3.7
Classifier: License :: OSI Approved :: MIT License
Classifier: Programming Language :: Python :: 3
Classifier: Programming Language :: Python :: 3.7
Classifier: Programming Language :: Python :: 3.8
Classifier: Programming Language :: Python :: 3.9
Classifier: Programming Language :: Python :: 3.10
Classifier: Programming Language :: Python :: 3.11
Requires-Dist: anywidget
Requires-Dist: traitlets>=5.0.0
Project-URL: Homepage, https://github.com/clevermaps/cm-jupyter-widget
